[
  {
    "title": "11 km S of Ula, Turkey",
    "type": "reviewed",
    "date": "2025.10.12 03:40:59",
    "lat": 37.0068,
    "lng": 28.4378,
    "md": "-.-",
    "ml": "-.-",
    "mw": "4.4",
    "depth": 10,
    "coordinates": [
      37.0068,
      28.4378
    ],
    "geojson": {
      "type": "Point",
      "coordinates": [
        28.4378,
        37.0068,
        10
      ]
    },
    "location_properties": "",
    "date_day": "2025.10.12",
    "date_hour": "03:40:59",
    "timestamp": false,
    "location_tz": "",
    "city": ""
  }
]